<keymap version="1" name="Default copy 2" parent="$default">
  <action id="CloseAllEditorsButActive">
    <keyboard-shortcut first-keystroke="ctrl m" />
  </action>
  <action id="CloseContent">
    <keyboard-shortcut first-keystroke="ctrl w" />
  </action>
  <action id="EditorCompleteStatement">
    <keyboard-shortcut first-keystroke="shift enter" />
  </action>
  <action id="EditorScrollToCenter" />
  <action id="EditorSelectWord">
    <keyboard-shortcut first-keystroke="ctrl 1" />
  </action>
  <action id="EditorStartNewLine" />
  <action id="ScrollPane-unitScrollLeft">
    <mouse-shortcut keystroke="control button143" />
  </action>
  <action id="ScrollPane-unitScrollRight">
    <mouse-shortcut keystroke="control button142" />
  </action>
  <action id="UpdateRunningApplication" />
  <action id="android.deploy.ApplyChanges">
    <keyboard-shortcut first-keystroke="ctrl f10" />
  </action>
  <action id="android.deploy.CodeSwap">
    <keyboard-shortcut first-keystroke="ctrl alt f10" />
  </action>
</keymap>